pypasreporter/__init__.py
pypasreporter/cli.py
pypasreporter/core.py
pypasreporter/py.typed
pypasreporter-0.2.0.dist-info/METADATA
pypasreporter-0.2.0.dist-info/WHEEL
pypasreporter-0.2.0.dist-info/entry_points.txt
pypasreporter-0.2.0.dist-info/RECORD
